<?xml version="1.0"?>
<PropertyList>

<model>
  <path>Models/Effects/pos_lamp_red_light_2st.xml</path>
  <offsets>
    <x-m>-502.153</x-m>
    <y-m>785.091</y-m>
    <z-m>133.215</z-m>
    <pitch-deg> 0.00</pitch-deg>
    <heading-deg>0.0 </heading-deg>
  </offsets>
</model>

<model>
  <path>Models/Effects/pos_lamp_red_light_2st.xml</path>
  <offsets>
    <x-m>-497.329</x-m>
    <y-m>803</y-m>
    <z-m>133.215</z-m>
    <pitch-deg> 0.00</pitch-deg>
    <heading-deg>0.0 </heading-deg>
  </offsets>
</model>

<model>
  <path>Models/Effects/pos_lamp_red_light_2st.xml</path>
  <offsets>
    <x-m>-507.835</x-m>
    <y-m>789.529</y-m>
    <z-m>133.215</z-m>
    <pitch-deg> 0.00</pitch-deg>
    <heading-deg>0.0 </heading-deg>
  </offsets>
</model>

<model>
  <path>Models/Effects/pos_lamp_red_light_2st.xml</path>
  <offsets>
    <x-m>-507.835</x-m>
    <y-m>789.529</y-m>
    <z-m>133.215</z-m>
    <pitch-deg> 0.00</pitch-deg>
    <heading-deg>0.0 </heading-deg>
  </offsets>
</model>

<model>
  <path>Models/Effects/pos_lamp_red_light_2st.xml</path>
  <offsets>
    <x-m>-474.859</x-m>
    <y-m>763.443</y-m>
    <z-m>100.062</z-m>
    <pitch-deg> 0.00</pitch-deg>
    <heading-deg>0.0 </heading-deg>
  </offsets>
</model>

<model>
  <path>Models/Effects/pos_lamp_red_light_2st.xml</path>
  <offsets>
    <x-m>-464.599</x-m>
    <y-m>776.75</y-m>
    <z-m>100.062</z-m>
    <pitch-deg> 0.00</pitch-deg>
    <heading-deg>0.0 </heading-deg>
  </offsets>
</model>

<model>
  <path>Models/Effects/pos_lamp_red_light_2st.xml</path>
  <offsets>
    <x-m>-470.437</x-m>
    <y-m>781.148</y-m>
    <z-m>100.062</z-m>
    <pitch-deg> 0.00</pitch-deg>
    <heading-deg>0.0 </heading-deg>
  </offsets>
</model>

<model>
  <path>Models/Effects/pos_lamp_red_light_2st.xml</path>
  <offsets>
    <x-m>-470.437</x-m>
    <y-m>781.148</y-m>
    <z-m>100.062</z-m>
    <pitch-deg> 0.00</pitch-deg>
    <heading-deg>0.0 </heading-deg>
  </offsets>
</model>
</PropertyList>
