<?xml version="1.0"?>
<PropertyList>

<model>
  <path>Models/Effects/pos_lamp_red_light_2st.xml</path>
  <offsets>
    <x-m>-284.213</x-m>
    <y-m>-446.313</y-m>
    <z-m>75.7686</z-m>
    <pitch-deg> 0.00</pitch-deg>
    <heading-deg>0.0 </heading-deg>
  </offsets>
</model>

<model>
  <path>Models/Effects/pos_lamp_red_light_2st.xml</path>
  <offsets>
    <x-m>-263.982</x-m>
    <y-m>-438.51</y-m>
    <z-m>75.7686</z-m>
    <pitch-deg> 0.00</pitch-deg>
    <heading-deg>0.0 </heading-deg>
  </offsets>
</model>

<model>
  <path>Models/Effects/pos_lamp_red_light_2st.xml</path>
  <offsets>
    <x-m>-277.759</x-m>
    <y-m>-419.846</y-m>
    <z-m>75.7686</z-m>
    <pitch-deg> 0.00</pitch-deg>
    <heading-deg>0.0 </heading-deg>
  </offsets>
</model>

<model>
  <path>Models/Effects/pos_lamp_red_light_2st.xml</path>
  <offsets>
    <x-m>-292.762</x-m>
    <y-m>-428.808</y-m>
    <z-m>75.7686</z-m>
    <pitch-deg> 0.00</pitch-deg>
    <heading-deg>0.0 </heading-deg>
  </offsets>
</model>
</PropertyList>
